steamguardgenpy/__init__.py
steamguardgenpy/guard.py
steamguardgenpy-0.1.dist-info/LICENSE
steamguardgenpy-0.1.dist-info/METADATA
steamguardgenpy-0.1.dist-info/WHEEL
steamguardgenpy-0.1.dist-info/top_level.txt
steamguardgenpy-0.1.dist-info/RECORD
