Metadata-Version: 2.1
Name: steamguardgenpy
Version: 0.1
Summary: Generate steam twofactor (onetime/TOTP) code.
Home-page: https://github.com/paradox4280/steamguardgenpy
Author: paradox4280
License: MIT
License-File: LICENSE
